octavia/__init__.py
octavia/i18n.py
octavia/opts.py
octavia/version.py
octavia/amphorae/__init__.py
octavia/amphorae/backends/__init__.py
octavia/amphorae/backends/agent/__init__.py
octavia/amphorae/backends/agent/agent_jinja_cfg.py
octavia/amphorae/backends/agent/api_server/__init__.py
octavia/amphorae/backends/agent/api_server/amphora_info.py
octavia/amphorae/backends/agent/api_server/certificate_update.py
octavia/amphorae/backends/agent/api_server/haproxy_compatibility.py
octavia/amphorae/backends/agent/api_server/keepalived.py
octavia/amphorae/backends/agent/api_server/keepalivedlvs.py
octavia/amphorae/backends/agent/api_server/loadbalancer.py
octavia/amphorae/backends/agent/api_server/lvs_listener_base.py
octavia/amphorae/backends/agent/api_server/osutils.py
octavia/amphorae/backends/agent/api_server/plug.py
octavia/amphorae/backends/agent/api_server/rules_schema.py
octavia/amphorae/backends/agent/api_server/server.py
octavia/amphorae/backends/agent/api_server/util.py
octavia/amphorae/backends/agent/api_server/templates/amphora-netns.systemd.j2
octavia/amphorae/backends/agent/api_server/templates/keepalived.systemd.j2
octavia/amphorae/backends/agent/api_server/templates/keepalived_check_script.conf.j2
octavia/amphorae/backends/agent/api_server/templates/keepalived_lvs_check_script.sh.j2
octavia/amphorae/backends/agent/api_server/templates/systemd.conf.j2
octavia/amphorae/backends/agent/templates/amphora_agent_conf.template
octavia/amphorae/backends/health_daemon/__init__.py
octavia/amphorae/backends/health_daemon/health_daemon.py
octavia/amphorae/backends/health_daemon/health_sender.py
octavia/amphorae/backends/health_daemon/status_message.py
octavia/amphorae/backends/utils/__init__.py
octavia/amphorae/backends/utils/haproxy_query.py
octavia/amphorae/backends/utils/interface.py
octavia/amphorae/backends/utils/interface_file.py
octavia/amphorae/backends/utils/ip_advertisement.py
octavia/amphorae/backends/utils/keepalivedlvs_query.py
octavia-17.0.0.dist-info/AUTHORS
octavia-17.0.0.dist-info/LICENSE
octavia-17.0.0.dist-info/METADATA
octavia-17.0.0.dist-info/WHEEL
octavia-17.0.0.dist-info/entry_points.txt
octavia-17.0.0.dist-info/pbr.json
octavia-17.0.0.dist-info/top_level.txt
octavia-17.0.0.dist-info/RECORD
