Metadata-Version: 2.1
Name: octavia
Version: 17.0.0
Summary: OpenStack Octavia Scalable Load Balancer as a Service
Home-page: https://docs.openstack.org/octavia/latest/
Author: OpenStack
Author-email: openstack-discuss@lists.openstack.org
Classifier: Development Status :: 5 - Production/Stable
Classifier: Environment :: OpenStack
Classifier: Intended Audience :: Developers
Classifier: Intended Audience :: Information Technology
Classifier: Intended Audience :: System Administrators
Classifier: License :: OSI Approved :: Apache Software License
Classifier: Operating System :: POSIX :: Linux
Classifier: Programming Language :: Python
Classifier: Programming Language :: Python :: 3
Classifier: Programming Language :: Python :: 3.10
Classifier: Programming Language :: Python :: 3.11
Classifier: Programming Language :: Python :: 3.12
Requires-Python: >=3.10
License-File: LICENSE
License-File: AUTHORS
Requires-Dist: alembic >=0.9.6
Requires-Dist: cotyledon >=1.3.0
Requires-Dist: pecan >=1.3.2
Requires-Dist: pbr >=3.1.1
Requires-Dist: SQLAlchemy >=1.2.19
Requires-Dist: SQLAlchemy-Utils >=0.30.11
Requires-Dist: futurist >=1.2.0
Requires-Dist: requests >=2.23.0
Requires-Dist: rfc3986 >=1.2.0
Requires-Dist: keystoneauth1 >=3.4.0
Requires-Dist: keystonemiddleware >=9.5.0
Requires-Dist: WebOb >=1.8.2
Requires-Dist: stevedore >=1.20.0
Requires-Dist: openstacksdk >=0.103.0
Requires-Dist: oslo.config >=6.8.0
Requires-Dist: oslo.context >=2.22.0
Requires-Dist: oslo.db[mysql] >=8.4.0
Requires-Dist: oslo.i18n >=3.20.0
Requires-Dist: oslo.log >=4.3.0
Requires-Dist: oslo.messaging >=14.1.0
Requires-Dist: oslo.middleware >=4.0.1
Requires-Dist: oslo.policy >=4.5.0
Requires-Dist: oslo.reports >=1.18.0
Requires-Dist: oslo.serialization >=2.28.1
Requires-Dist: oslo.upgradecheck >=1.3.0
Requires-Dist: oslo.utils >=4.7.0
Requires-Dist: psutil >=5.7.1
Requires-Dist: pyasn1 !=0.2.3,>=0.1.8
Requires-Dist: pyasn1-modules >=0.0.6
Requires-Dist: python-barbicanclient >=4.5.2
Requires-Dist: python-glanceclient >=2.8.0
Requires-Dist: python-novaclient >=9.1.0
Requires-Dist: python-cinderclient >=3.3.0
Requires-Dist: WSME >=0.8.0
Requires-Dist: Jinja2 >=2.10
Requires-Dist: taskflow >=5.9.0
Requires-Dist: castellan >=0.16.0
Requires-Dist: tenacity >=5.0.4
Requires-Dist: distro >=1.2.0
Requires-Dist: jsonschema >=3.2.0
Requires-Dist: octavia-lib >=3.8.0
Requires-Dist: setproctitle >=1.1.10
Requires-Dist: python-dateutil >=2.7.0
Requires-Dist: Flask !=0.11,>=0.10
Requires-Dist: cryptography >=42.0.0
Requires-Dist: gunicorn >=19.9.0
Requires-Dist: Werkzeug >=0.14.1
Requires-Dist: pyroute2 >=0.5.14 ; (sys_platform!='win32')
Provides-Extra: etcd
Requires-Dist: etcd3gw >=2.4.1 ; extra == 'etcd'
Provides-Extra: redis
Requires-Dist: redis >=3.4.0 ; extra == 'redis'
Provides-Extra: test
Requires-Dist: hacking <6.2.0,>=6.1.0 ; extra == 'test'
Requires-Dist: requests-mock >=1.2.0 ; extra == 'test'
Requires-Dist: coverage !=4.4,>=4.0 ; extra == 'test'
Requires-Dist: fixtures >=3.0.0 ; extra == 'test'
Requires-Dist: flake8-import-order <0.19.0,>=0.18.0 ; extra == 'test'
Requires-Dist: oslotest >=3.2.0 ; extra == 'test'
Requires-Dist: pylint >=2.5.3 ; extra == 'test'
Requires-Dist: stestr >=2.0.0 ; extra == 'test'
Requires-Dist: testrepository >=0.0.18 ; extra == 'test'
Requires-Dist: testtools >=2.2.0 ; extra == 'test'
Requires-Dist: testresources >=2.0.0 ; extra == 'test'
Requires-Dist: testscenarios >=0.4 ; extra == 'test'
Requires-Dist: doc8 >=0.6.0 ; extra == 'test'
Requires-Dist: bandit !=1.6.0,>=1.1.0 ; extra == 'test'
Requires-Dist: sphinx !=2.1.0,>=2.0.0 ; extra == 'test'
Requires-Dist: bashate >=0.5.1 ; extra == 'test'
Requires-Dist: WebTest >=2.0.26 ; extra == 'test'
Provides-Extra: zookeeper
Requires-Dist: kazoo >=2.6.0 ; extra == 'zookeeper'
